LICENSE
MANIFEST.in
README.md
VERSION
archive-man.py
setup.py
apt_archive_tools/__init__.py
apt_archive_tools/archive_man.py
apt_archive_tools.egg-info/PKG-INFO
apt_archive_tools.egg-info/SOURCES.txt
apt_archive_tools.egg-info/dependency_links.txt
apt_archive_tools.egg-info/entry_points.txt
apt_archive_tools.egg-info/requires.txt
apt_archive_tools.egg-info/top_level.txt
apt_archive_tools/contrib/__init__.py
apt_archive_tools/contrib/docopt.py
apt_archive_tools/contrib/ftparchive.py
apt_archive_tools/contrib/gnupg.py
apt_archive_tools/lib/__init__.py
apt_archive_tools/lib/check.py
apt_archive_tools/lib/checkdep.py
apt_archive_tools/lib/config.py
apt_archive_tools/lib/copy_archive.py
apt_archive_tools/lib/default.conf
apt_archive_tools/lib/diff.py
apt_archive_tools/lib/key.py
apt_archive_tools/lib/local_copy.py
apt_archive_tools/lib/merge.py
apt_archive_tools/lib/publish.py
apt_archive_tools/lib/rename.py
apt_archive_tools/lib/sign.py
apt_archive_tools/lib/strip.py
apt_archive_tools/lib/utils.py
test/test_deb822.py