Metadata-Version: 2.1
Name: apt-archive-tools
Version: 1.1.0.dev27
Summary: Apt archive toolkit
Home-page: https://github.com/sir-xw/apt-archive-tools
Author: Xie Wei
Author-email: xw.master@live.cn
License: GPLv2
Platform: UNKNOWN
Classifier: Programming Language :: Python :: 2.7
Classifier: Programming Language :: Python :: 3
Classifier: License :: OSI Approved :: GNU General Public License v2 (GPLv2)
Classifier: Operating System :: POSIX :: Linux
